names_generator/__init__.py
names_generator/__meta__.py
names_generator/names.py
names_generator-0.1.0.dist-info/LICENSE
names_generator-0.1.0.dist-info/METADATA
names_generator-0.1.0.dist-info/WHEEL
names_generator-0.1.0.dist-info/entry_points.txt
names_generator-0.1.0.dist-info/top_level.txt
names_generator-0.1.0.dist-info/RECORD
