Metadata-Version: 2.1
Name: names-generator
Version: 0.1.0
Summary: Clone of the Moby/Docker random name generator as a Python package.
Home-page: https://github.com/glentner/names_generator
Author: Geoffrey Lentner
Author-email: glentner@purdue.edu
License: Apache License
Keywords: random name generator
Platform: UNKNOWN
Classifier: Development Status :: 5 - Production/Stable
Classifier: Topic :: Software Development :: Libraries :: Application Frameworks
Classifier: License :: OSI Approved :: Apache Software License
Classifier: Programming Language :: Python :: 3.7
Classifier: Programming Language :: Python :: 3.8
Classifier: Programming Language :: Python :: 3.9
Requires-Dist: cmdkit (>=2.1.2)
